{"data":{"site":{"siteMetadata":{"title":"kohsweblog","author":"koh110"}},"markdownRemark":{"id":"607126d7-a20c-5ac4-b10e-a5d67a2e4834","excerpt":"このブログは静的サイトジェネレータの GatsbyJS で作っています。はじめて触ってみて、ちょっとクセを感じるなぁという感想です。プラグインを作成しようとしてみたら、 というディレクトリを作る必要性があったり、その中のディレクトリ構成やファイル名などが固定化されるなどなど。way…","html":"<p>このブログは静的サイトジェネレータの GatsbyJS で作っています。</p>\n<p>はじめて触ってみて、ちょっとクセを感じるなぁという感想です。</p>\n<p>プラグインを作成しようとしてみたら、<code class=\"language-text\">plugins</code> というディレクトリを作る必要性があったり、その中のディレクトリ構成やファイル名などが固定化されるなどなど。</p>\n<p>way に乗らなければならない部分が多そうという初見の印象。</p>\n<p>触っていって印象が変わってきたら、また記事としてのこしておきたい。</p>","frontmatter":{"title":"GatsbyJSでブログを作ってみる","date":"2019-01-01"}}},"pageContext":{"isCreatedByStatefulCreatePages":false,"slug":"/hello-world/","previous":null,"next":{"fields":{"slug":"/chat/"},"frontmatter":{"title":"チャットシステムを作るときに知っておくべきこと"}}}}